django_molder/templatetags
django_molder
django_molder/renderers
