Metadata-Version: 1.1
Name: django-molder
Version: 0.1.0
Summary: Another one painless way to working with forms and they fields
Home-page: https://github.com/zerc/django_molder
Author: Vladimir Savin
Author-email: zero13cool@yandex.ru
License: BSD
Keywords: django_molder
Platform: UNKNOWN
Classifier: Development Status :: 2 - Pre-Alpha
Classifier: Intended Audience :: Developers
Classifier: License :: OSI Approved :: BSD License
Classifier: Natural Language :: English
Classifier: Programming Language :: Python :: 2
Classifier: Programming Language :: Python :: 2.7
Classifier: Programming Language :: Python :: 3
Classifier: Programming Language :: Python :: 3.3
Classifier: Programming Language :: Python :: 3.4
